Workbook

Sheet Sales Data
A1: Order ID | B1: Salesperson | C1: Region | D1: Product | E1: Category | F1: Date | G1: Qty | H1: Unit Price (₹) | I1: Discount (%) | J1: Revenue (₹) | K1: Profit (₹)
A2: ORD-001 | B2: Rahul Sharma | C2: North | D2: Laptop Pro | E2: Electronics | F2: 2024-01-05 | G2: 2 | H2: 55000 | I2: 5 | J2: =G2*H2*(1-I2/100) -> 104500 | K2: =J2*0.2 -> 20900
A3: ORD-002 | B3: Priya Singh | C3: South | D3: Office Chair | E3: Furniture | F3: 2024-01-08 | G3: 5 | H3: 8500 | I3: 10 | J3: =G3*H3*(1-I3/100) -> 38250 | K3: =J3*0.2 -> 7650
A4: ORD-003 | B4: Amit Verma | C4: East | D4: Smartphone X | E4: Electronics | F4: 2024-01-12 | G4: 10 | H4: 22000 | I4: 8 | J4: =G4*H4*(1-I4/100) -> 202400 | K4: =J4*0.2 -> 40480
A5: ORD-004 | B5: Sneha Patil | C5: West | D5: Desk Lamp | E5: Furniture | F5: 2024-01-15 | G5: 8 | H5: 1200 | I5: 0 | J5: =G5*H5*(1-I5/100) -> 9600 | K5: =J5*0.2 -> 1920
A6: ORD-005 | B6: Rahul Sharma | C6: North | D6: Tablet Air | E6: Electronics | F6: 2024-02-02 | G6: 3 | H6: 18000 | I6: 5 | J6: =G6*H6*(1-I6/100) -> 51300 | K6: =J6*0.2 -> 10260
A7: ORD-006 | B7: Karan Mehta | C7: South | D7: Wireless Mouse | E7: Electronics | F7: 2024-02-10 | G7: 15 | H7: 1500 | I7: 12 | J7: =G7*H7*(1-I7/100) -> 19800 | K7: =J7*0.2 -> 3960
A8: ORD-007 | B8: Priya Singh | C8: South | D8: Bookshelf | E8: Furniture | F8: 2024-02-18 | G8: 2 | H8: 6000 | I8: 0 | J8: =G8*H8*(1-I8/100) -> 12000 | K8: =J8*0.2 -> 2400
A9: ORD-008 | B9: Amit Verma | C9: East | D9: Laptop Pro | E9: Electronics | F9: 2024-02-22 | G9: 1 | H9: 55000 | I9: 5 | J9: =G9*H9*(1-I9/100) -> 52250 | K9: =J9*0.2 -> 10450
A10: ORD-009 | B10: Neha Joshi | C10: West | D10: Printer | E10: Electronics | F10: 2024-03-01 | G10: 4 | H10: 12000 | I10: 7 | J10: =G10*H10*(1-I10/100) -> 44640 | K10: =J10*0.2 -> 8928
A11: ORD-010 | B11: Karan Mehta | C11: South | D11: Monitor HD | E11: Electronics | F11: 2024-03-08 | G11: 6 | H11: 15000 | I11: 10 | J11: =G11*H11*(1-I11/100) -> 81000 | K11: =J11*0.2 -> 16200
A12: ORD-011 | B12: Sneha Patil | C12: West | D12: Office Chair | E12: Furniture | F12: 2024-03-15 | G12: 3 | H12: 8500 | I12: 5 | J12: =G12*H12*(1-I12/100) -> 24225 | K12: =J12*0.2 -> 4845
A13: ORD-012 | B13: Rahul Sharma | C13: North | D13: Wireless Mouse | E13: Electronics | F13: 2024-03-20 | G13: 20 | H13: 1500 | I13: 15 | J13: =G13*H13*(1-I13/100) -> 25500 | K13: =J13*0.2 -> 5100
... A21: ORD-020 | B21: Priya Singh | C21: South | D21: Smartphone X | E21: Electronics | F21: 2024-06-15 | G21: 8 | H21: 22000 | I21: 8 | J21: =G21*H21*(1-I21/100) -> 161920 | K21: =J21*0.2 -> 32384
A22: TOTAL | G22: =SUM(G2:G21) -> 120 | J22: =SUM(J2:J21) -> 1207985 | K22: =SUM(K2:K21) -> 241597

Sheet Summary
A1: Sales Summary - 2024
A3: Salesperson | B3: Total Orders | C3: Total Revenue (₹) | D3: Total Profit (₹)
A4: Rahul Sharma | B4: =COUNTIF('Sales Data'!B:B,A4) -> 4 | C4: =SUMIF('Sales Data'!B:B,A4,'Sales Data'!J:J) -> 203620 | D4: =SUMIF('Sales Data'!B:B,A4,'Sales Data'!K:K) -> 40724
A5: Priya Singh | B5: =COUNTIF('Sales Data'!B:B,A5) -> 4 | C5: =SUMIF('Sales Data'!B:B,A5,'Sales Data'!J:J) -> 316670 | D5: =SUMIF('Sales Data'!B:B,A5,'Sales Data'!K:K) -> 63334
A6: Amit Verma | B6: =COUNTIF('Sales Data'!B:B,A6) -> 3 | C6: =SUMIF('Sales Data'!B:B,A6,'Sales Data'!J:J) -> 269050 | D6: =SUMIF('Sales Data'!B:B,A6,'Sales Data'!K:K) -> 53810
A7: Sneha Patil | B7: =COUNTIF('Sales Data'!B:B,A7) -> 3 | C7: =SUMIF('Sales Data'!B:B,A7,'Sales Data'!J:J) -> 74325 | D7: =SUMIF('Sales Data'!B:B,A7,'Sales Data'!K:K) -> 14865
A8: Karan Mehta | B8: =COUNTIF('Sales Data'!B:B,A8) -> 3 | C8: =SUMIF('Sales Data'!B:B,A8,'Sales Data'!J:J) -> 168480 | D8: =SUMIF('Sales Data'!B:B,A8,'Sales Data'!K:K) -> 33696
A9: Neha Joshi | B9: =COUNTIF('Sales Data'!B:B,A9) -> 3 | C9: =SUMIF('Sales Data'!B:B,A9,'Sales Data'!J:J) -> 175840 | D9: =SUMIF('Sales Data'!B:B,A9,'Sales Data'!K:K) -> 35168
A10: Grand Total | B10: =SUM(B4:B9) -> 20 | C10: =SUM(C4:C9) -> 1207985 | D10: =SUM(D4:D9) -> 241597
